_SubnetTree.cpython-311-x86_64-linux-gnu.so
SubnetTree.py
hmt_pysubnettree-0.37.dist-info/WHEEL
hmt_pysubnettree-0.37.dist-info/RECORD
hmt_pysubnettree-0.37.dist-info/top_level.txt
hmt_pysubnettree-0.37.dist-info/COPYING
hmt_pysubnettree-0.37.dist-info/METADATA
