Metadata-Version: 2.1
Name: hmt-pysubnettree
Version: 0.37
Summary: The PySubnetTree package provides a Python data structure SubnetTree
Home-page: https://github.com/zeek/pysubnettree
License: BSD
Classifier: Development Status :: 5 - Production/Stable
Classifier: Environment :: Console
Classifier: License :: OSI Approved :: BSD License
Classifier: Operating System :: POSIX :: Linux
Classifier: Operating System :: POSIX :: BSD :: FreeBSD
Classifier: Operating System :: MacOS :: MacOS X
Classifier: Programming Language :: Python :: 3
Classifier: Topic :: System :: Networking
Classifier: Topic :: Utilities
License-File: COPYING
